griffe_fieldz/__init__.py
griffe_fieldz/_extension.py
griffe_fieldz/_repr.py
griffe_fieldz/py.typed
griffe_fieldz-0.4.0.dist-info/METADATA
griffe_fieldz-0.4.0.dist-info/WHEEL
griffe_fieldz-0.4.0.dist-info/licenses/LICENSE
griffe_fieldz-0.4.0.dist-info/RECORD
