Metadata-Version: 2.4
Name: griffe-fieldz
Version: 0.4.0
Summary: Griffe extension adding support for data-class like things (pydantic, attrs, etc...)
Project-URL: homepage, https://github.com/pyapp-kit/griffe-fieldz
Project-URL: repository, https://github.com/pyapp-kit/griffe-fieldz
Author-email: Talley Lambert <talley.lambert@example.com>
License: BSD-3-Clause
License-File: LICENSE
Classifier: Development Status :: 4 - Beta
Classifier: License :: OSI Approved :: BSD License
Classifier: Programming Language :: Python :: 3
Classifier: Programming Language :: Python :: 3.8
Classifier: Programming Language :: Python :: 3.9
Classifier: Programming Language :: Python :: 3.10
Classifier: Programming Language :: Python :: 3.11
Classifier: Programming Language :: Python :: 3.12
Classifier: Programming Language :: Python :: 3.13
Classifier: Programming Language :: Python :: 3.14
Classifier: Topic :: Documentation
Classifier: Topic :: Software Development
Classifier: Topic :: Software Development :: Documentation
Classifier: Topic :: Utilities
Classifier: Typing :: Typed
Requires-Python: >=3.9
Requires-Dist: fieldz>=0.1.0
Requires-Dist: griffe>=1.0
